verrific/__about__.py
verrific/__init__.py
verrific/core.py
verrific/pdf2grobid.py
verrific-0.1.1.dist-info/LICENSE
verrific-0.1.1.dist-info/METADATA
verrific-0.1.1.dist-info/WHEEL
verrific-0.1.1.dist-info/RECORD
