Metadata-Version: 2.3
Name: verrific
Version: 0.1.1
Summary: Python package for cross-checking and verifying references in scientific papers, designed for use with scienceverse/papercheck
License: MIT
Author: Jakub Werner
Author-email: jakubwerner1@proton.me
Requires-Python: >=3.13
Classifier: License :: OSI Approved :: MIT License
Classifier: Programming Language :: Python :: 3
Classifier: Programming Language :: Python :: 3.13
Requires-Dist: fastapi (>=0.116.1,<0.117.0)
Requires-Dist: httpx (>=0.28.1,<0.29.0)
Requires-Dist: lxml (>=6.0.0,<7.0.0)
Requires-Dist: pandas (>=2.3.1,<3.0.0)
Requires-Dist: pydantic (>=2.11.7,<3.0.0)
Requires-Dist: pytest (>=8.4.1,<9.0.0)
Requires-Dist: rapidfuzz (>=3.13.0,<4.0.0)
Requires-Dist: requests (>=2.32.4,<3.0.0)
Requires-Dist: scholarly (>=1.7.11,<2.0.0)
Requires-Dist: tenacity (>=9.1.2,<10.0.0)
Requires-Dist: tqdm (>=4.67.1,<5.0.0)
Requires-Dist: unidecode (>=1.4.0,<2.0.0)
